konch/__init__.py
konch/docopt.py
konch/py.typed
konch-6.0.1.dist-info/entry_points.txt
konch-6.0.1.dist-info/licenses/LICENSE
konch-6.0.1.dist-info/WHEEL
konch-6.0.1.dist-info/METADATA
konch-6.0.1.dist-info/RECORD
